nujo/__init__.py
nujo/_cache.py
nujo/autodiff/__init__.py
nujo/autodiff/_functions/__init__.py
nujo/autodiff/_functions/_activations.py
nujo/autodiff/_functions/_aggregate.py
nujo/autodiff/_functions/_elementary.py
nujo/autodiff/_functions/_transform.py
nujo/autodiff/_functions/_trigonometric.py
nujo/autodiff/_node.py
nujo/autodiff/_utils.py
nujo/autodiff/function.py
nujo/autodiff/modes.py
nujo/autodiff/tensor.py
nujo/flow.py
nujo/init/__init__.py
nujo/init/basic.py
nujo/init/random.py
nujo/math/__init__.py
nujo/math/aggregate.py
nujo/math/scalar.py
nujo/nn/__init__.py
nujo/nn/activations.py
nujo/nn/layers.py
nujo/objective/__init__.py
nujo/objective/loss.py
nujo/objective/qualitative.py
nujo/objective/quantitative.py
nujo/optim/__init__.py
nujo/optim/optimizer.py
nujo/optim/optimizers.py
nujo/utils/__init__.py
nujo/utils/computation_graph_plotter.py
nujo-0.3.0.dist-info/LICENSE
nujo-0.3.0.dist-info/WHEEL
nujo-0.3.0.dist-info/METADATA
nujo-0.3.0.dist-info/RECORD
